{
  "stage_id": 4,
  "name": "鏡の反転",
  "assets": {
    "background": "bg_stage_04.png",
    "door": "door_mirror.png",
    "bgm": "ambient_mystery_02.mp3"
  },
  "interactables": [
    { "id": "mirror",       "rect": [150, 150, 140, 200], "zoom_image": "mirror_8012_zoom.png", "reveals": "2108(reflected:8012)" },
    { "id": "wall_number",  "rect": [40, 300, 80, 40],    "zoom_image": "wall_number_zoom.png",  "reveals": "8012" },
    {
      "id": "hidden_drawer",
      "rect": [200, 470, 70, 40],
      "zoom_image": "drawer_open_zoom.png",
      "gives_item": "item_culprit_evidence",
      "hidden": true
    }
  ],
  "gimmick": {
    "type": "text_input",
    "solutions": { "normal": "2108" },
    "validate": "exact"
  },
  "hard": {
    "modifiers": ["cipher", "indirection"],
    "interactables": [
      { "id": "mirror",      "rect": [150, 150, 140, 200], "zoom_image": "mirror_glyph_zoom.png", "reveals_glyphs_reflected": ["g_8", "g_0", "g_1", "g_2"] },
      { "id": "wall_number", "rect": [40, 300, 80, 40],    "zoom_image": "wall_glyph_zoom.png",   "reveals_glyphs": ["g_8", "g_0", "g_1", "g_2"] },
      { "id": "hidden_drawer", "rect": [200, 470, 70, 40], "zoom_image": "drawer_open_zoom.png", "gives_item": "item_culprit_evidence", "hidden": true }
    ],
    "gimmick": {
      "type": "text_input",
      "solutions": { "hard": "2108" },
      "validate": "exact"
    },
    "decode_hint": "鏡像の回廊文字をまず解読し（8012）、さらに左右反転を戻す（2108）。二重の手数。"
  },
  "hints": ["h_s04_1", "h_s04_2"],
  "rewards": {
    "memory_id": "mem_04",
    "text_full": "t_s04_full",
    "text_corrupt": "t_s04_corrupt",
    "item": "item_diary"
  }
}
