{
  "_meta": { "lang": "ja", "note": "全文言をIDで集約。多言語化時は text_en.json 等を追加する。" },

  "h_s01_1": "壁の絵画を調べてみよう。",
  "h_s01_2": "絵画の隅に、小さな数字が描かれている。",
  "h_s01_3": "その数字『1024』をテンキーに入力する。",
  "h_s02_1": "床に散らばった本に注目しよう。",
  "h_s02_2": "本の色の並び順が、ボタンを押す順番だ。",
  "h_s02_3": "青→黄→赤→緑 の順にボタンを押す。",
  "h_s03_1": "時計とスマホ、両方を調べよう。",
  "h_s03_2": "止まった時計の時刻は当てにならない。『今の時刻』は別の場所にある。",
  "h_s03_3": "スマホの現在時刻【04:15】＝『0415』が答え。",
  "h_s04_1": "ドアの鏡に、何かが映り込んでいる。",
  "h_s04_2": "鏡像は左右が反転している。元の数字は壁にある。",
  "h_s04_3": "『8012』を反転させた『2108』を入力する。",
  "h_s05_1": "明かりがある限り、状況がつかめない。",
  "h_s05_2": "ブレーカーを切って暗闇にすると、状況が見える。",
  "h_s05_3": "ここに“正解”は無い。あなたの選択が物語を決める。",
  "t_s05_examine": "震える手で、血に濡れた“それ”を写真に収めた。目を逸らさない。たとえ写っているのが自分の罪だとしても、知らないままでは何も始まらない。サイレンが近い。私はドアを開けた。",
  "t_s05_hide": "見たくなかった。血の付いた“それ”を布で拭い、暗がりの隅へ蹴り込む。何も無かった。何も見ていない。そう言い聞かせて、私はドアを開けた。サイレンが、近い。",

  "t_s01_full":    "ドアが開いた。…いや、開けてしまった。目の前には、さらに奥へと続く薄暗い廊下。なぜだろう、自分の両手が不自然に赤い。これは、血……？",
  "t_s01_corrupt": "ドアが勝手に開いた…頭が割れそうに痛い。ウッ……手が……赤い……？（記憶が一部欠落した）",

  "t_s02_full":    "床に落ちていた紙切れを拾った。この洋館の主からの招待状だ。『今夜20時、私の書斎へお越しください』。そうだ、私は誰かに呼び出されてここに来たんだ。でも、誰に？",
  "t_s02_corrupt": "紙切れを拾った。招待状……？　『今夜20時、■■の書斎へ』。誰かに呼ばれた気がする。でも、誰だったか思い出せない。（記憶が一部欠落した）",

  "t_s03_full":    "ポケットの中でスマホが震えた。画面を見るが『圏外』。表示された現在時刻は【04:15】。さっきの時計は30分前を指していた。あの時間、この館で何が起きた？",
  "t_s03_corrupt": "スマホが震えた。圏外。時刻は【0■:■5】……？　さっきの時計との差が、何か意味を持っていた気がするのに。（記憶が一部欠落した）",

  "t_s04_full":    "ドアの隙間に日記のページが挟まれていた。館の主の文字だ。『奴が私を狙っている。あの狂気に満ちた目を私は忘れない』。ゾッとした。主を狙う犯人……それは、私なのか…？",
  "t_s04_corrupt": "日記のページ。館の主の字……『奴が私を狙っ■■■』。狂気の目。狙っていたのは……私？　それとも……。（記憶が一部欠落した）",

  "t_s05_full":    "遠くから、微かにパトカーのサイレンの音が聞こえた気がした。通報された？　誰が？　恐怖で心臓がバクバクと鳴り響く。早くここから出ないと捕まる。",
  "t_s05_corrupt": "サイレン……の音？　通報。誰が。心臓がうるさい。捕まる、捕まる、捕まる。（記憶が一部欠落した）",

  "h_s06_1": "肖像画と棚をよく調べよう。",
  "h_s06_2": "老人が持つ駒＝1個、棚の駒＝その数。台座に押す順番が刻まれている。",
  "h_s06_3": "ポーン3→ナイト1→ルーク2（歩歩歩→騎→城城）の順に押す。",
  "t_s06_full":    "肖像画の老人——この館の主だ。チェスに見立てた配置。私と主は、何度もこの盤を挟んだ記憶がある。私たちは、友人だったのか？",
  "t_s06_corrupt": "肖像画の老人……主？　盤を挟んだ記憶……相手は誰だった？（記憶が一部欠落した）",

  "h_s07_1": "暗くて薬品棚の奥が見えない。",
  "h_s07_2": "レバーを引くとバックライトが点く。ボトルの影が数字の形になる。",
  "h_s07_3": "影が示す数字『3514』を入力する。",
  "t_s07_full":    "薬品棚の奥に、見覚えのある小瓶。ラベルには——私の名前。なぜ私の薬がこの館に常備されている？　私はここに、通っていたのか？",
  "t_s07_corrupt": "薬品棚……私の名前のラベル？　なぜ、ここに……（記憶が一部欠落した）",

  "h_s08_1": "壁のA〜Dと、床の血痕の図形を見比べよう。",
  "h_s08_2": "A=◯ B=☆ C=□ D=△。A→B→C→D の順に対応図形を押す。",
  "h_s08_3": "◯→☆→□→△ の順に押す。",
  "t_s08_full":    "血痕は床に点々と続き、形を辿るとドアの外へ。これは——引きずった跡だ。誰かがここから運び出された。その『誰か』は、いったい。",
  "t_s08_corrupt": "血の跡……外へ続く……運ばれた？　誰が、誰を……（記憶が一部欠落した）",

  "h_s09_1": "カレンダーの焼け残りとメモを調べよう。",
  "h_s09_2": "メモは『10月の第3金曜』。金曜の列から第3週の日付を数える。",
  "h_s09_3": "10月16日＝『1016』を入力する。",
  "t_s09_full":    "第3金曜——今日だ。『約束』の日。焦げたカレンダーの裏に走り書きがあった。『彼が来る前に、終わらせる』。終わらせる、とは……何を？",
  "t_s09_corrupt": "第3金曜……今日……『終わらせる』……何を？（記憶が一部欠落した）",

  "h_s10_1": "明かりを消すと、暖炉の中に何かが見える。",
  "h_s10_2": "暗闇でドアノブを拾い、取付部に使う。暗号は獣の数字を並び順に。",
  "h_s10_3": "熊3・鷲1・狼8、並びは[狼][熊][鷲]＝『831』。",
  "t_s10_full":    "暖炉の獣が指し示した数字でドアノブを得た。冷たい金属の感触。この手は、確かにこれを握ったことがある。私は何度も、この部屋を出入りしていたんだ。",
  "t_s10_corrupt": "暖炉……数字……ドアノブの感触だけが残る。私は、ここの……住人？（記憶が一部欠落した）",

  "h_s11_1": "破れた紙片を、枠へドラッグして組み合わせよう。",
  "h_s11_2": "絵柄と文字のつながりを見て、上下の位置を合わせる。",
  "h_s11_3": "紙片A＝中段、B＝下段、C＝上段 に置く。",
  "t_s11_full": "破れたカルテを継ぎ合わせた。患者名の欄に——私の名前が書かれている。診断名は黒く塗り潰され、読めない。私は、この館の“患者”だったのか？",
  "t_s11_corrupt": "カルテ……患者名は、私？　診断名は黒く塗り潰されて……（記憶が一部欠落した）",

  "h_s12_1": "レコーダーとラジオ、両方を調べよう。",
  "h_s12_2": "レコーダー裏の『FM 80.2』が、ラジオの周波数だ。",
  "h_s12_3": "ラジオに『802』を合わせる。",
  "t_s12_full": "周波数を合わせると、ノイズの奥から声が滲み出た——私の声だ。『先生、もう…限界です』。私は誰に、何を訴えていたんだ。",
  "t_s12_corrupt": "ノイズの奥に声……私の声？　『先生、もう…』そこで途切れる。（記憶が一部欠落した）",

  "h_s13_1": "床の足跡をよく見よう。白と血、2種類ある。",
  "h_s13_2": "血の足跡は罠。白い足跡の向きの順にボタンを押す。",
  "h_s13_3": "↑ → ↓ ← の順に押す。",
  "t_s13_full": "白い足跡を辿るとドアに着いた。だが血の足跡は——何かを引きずって、奥の闇へ消えている。運び出されたのは、いったい誰だったのか。",
  "t_s13_corrupt": "白い足跡、血の足跡……引きずった跡が奥へ。運ばれたのは……（記憶が一部欠落した）",

  "t_final_prompt": "外からサイレンが響く。私は一体、何者なんだ？",

  "t_final_deduction_q": "（記憶を整理する）集めた記憶から、自分は何者だと結論づける？",
  "t_ded_opt_witness": "館の主に招かれ、別の何者かの凶行に巻き込まれた『目撃者』だ。",
  "t_ded_opt_culprit": "この手の赤さがすべてを物語っている。私が『犯人』だ。",
  "t_ded_opt_unknown": "……分からない。記憶が欠けすぎていて、何も結論できない。",

  "t_end_A_true": "【Ending A＋：真・無実の証明】整理された記憶が、一本の線で真相を描き出す。あなたは招待状を、日記を、すべての証拠を警察に差し出した。震える手が指し示す先で、真犯人が崩れ落ちる。あなたの無実は、完全に証明された。",
  "t_end_A":  "【Ending A：無実の証明】警察が突入し、主人公は保護された。集めた証拠が真犯人を追い詰め、逮捕に至る。すべての記憶が、あなたの無実を証明した。",
  "t_end_A2": "【Ending A′：疑惑の保護】警察に保護されたものの、欠けた記憶が災いし、あなた自身に疑いの目が向けられる。真相は、宙づりのまま。",
  "t_end_B":  "【Ending B：終わらない逃亡】隠し通路の先で、真犯人が待ち伏せていた。視界が暗転し――気づけば、また、あの白い部屋。すべてが、最初から繰り返される。",
  "t_end_B2": "【Ending B′：逃亡の代償】逃げ切った。だが本当は、逃げる必要などなかった。真実に背を向けたあなたは、永遠に自分が何者かを知らないまま生きていく。",
  "t_end_C":  "【Ending C：共犯者の告発】あなたは犯人の動機を知る共犯者――いや、復讐者だった。遺留品を握りしめ、夜霧に紛れて洋館を去る。事件のすべては、闇に葬られた。",
  "t_end_C2": "【Ending C′：ただの逃走】裏口の鍵は、あっけなく開いた。あなたは何も解決しないまま、夜の闇へ消えていく。真相は、誰にも知られることはなかった。"
}
